{
  "name": "Super Mech Armor",
  "id": 1511,
  "tier": 1,
  "rank": [
    "Special"
  ],
  "buildsFrom": [],
  "buildsInto": [],
  "specialRecipe": 0,
  "noEffects": false,
  "removed": false,
  "requiredChampion": "",
  "requiredAlly": "",
  "icon": "https://raw.communitydragon.org/15.10/plugins/rcp-be-lol-game-data/global/default/assets/items/icons2d/1511_supermecharmor.png",
  "simpleDescription": null,
  "nicknames": [],
  "passives": [
    {
      "name": null,
      "unique": true,
      "effects": "<img src=\"/img/icons/turret.webp\" class=\"tip-icon\" />Turret basic attacks are modified to deal 7% of this minion's <b>maximum</b> health as pre-mitigation damage.",
      "cooldown": null,
      "range": null
    }
  ],
  "active": [],
  "stats": {},
  "shop": {
    "prices": {
      "total": 0,
      "combined": 0,
      "sell": 0
    },
    "purchasable": false,
    "tags": []
  },
  "iconOverlay": false,
  "maps": [
    11,
    12,
    21,
    30,
    35
  ]
}