{
  "name": "Runic Compass",
  "id": 3866,
  "tier": 2,
  "rank": [
    "Epic"
  ],
  "buildsFrom": [],
  "buildsInto": [],
  "specialRecipe": 3865,
  "noEffects": false,
  "removed": false,
  "requiredChampion": "",
  "requiredAlly": "",
  "icon": "https://raw.communitydragon.org/15.10/plugins/rcp-be-lol-game-data/global/default/assets/items/icons2d/3866_runiccompass.png",
  "simpleDescription": null,
  "nicknames": [],
  "passives": [
    {
      "name": "Support Quest",
      "unique": true,
      "effects": "Earn 800 through <i>Shared Riches</i> to automatically upgrade to {{ii|Bounty of Worlds}}, increasing the <i>Ward</i> active to instead have 4 wards in stock.",
      "cooldown": null,
      "range": null
    },
    {
      "name": "Shared Riches",
      "unique": true,
      "effects": "Grants a <b>Shared Riches</b> charge every 20 seconds, up to 3 charges. When an allied champion is within <img src=\"/img/icons/er.png\" loading=\"lazy\" class=\"tip-icon\" decoding=\"async\" />icononly=true 1050 units of you, consume a charge in the following ways:<br>• Kill a minion by any means, granting you 20 and the nearest allied champion kill {{g|gold}}. Damaging a minion <b>below</b> {{rd|50%|30%}} of its <b>maximum</b> health <img src=\"/img/icons/execute.png\" loading=\"lazy\" class=\"tip-icon\" decoding=\"async\" />executes it.<br>• Damage an enemy champion or structure with a basic attack or ability, granting you 24. A charge may be consumed this way only once per attack or ability.",
      "cooldown": null,
      "range": null
    },
    {
      "name": null,
      "unique": true,
      "effects": "Receives diminishing gold from excessive minion kills.",
      "cooldown": null,
      "range": null
    }
  ],
  "active": [
    {
      "name": "Ward",
      "unique": true,
      "effects": "Consumes a charge to place a <img src=\"/img/icons/stealth%20ward.png\" loading=\"lazy\" class=\"tip-icon\" decoding=\"async\" />Stealth Ward at the target location, which grants <img src=\"/img/icons/sight.png\" loading=\"lazy\" class=\"tip-icon\" decoding=\"async\" />sight of the surrounding area. <b>Warding</b> charges refill upon visiting the shop.",
      "cooldown": null,
      "range": 600
    }
  ],
  "stats": {
    "goldPer10": 5,
    "health": 100,
    "healthRegen": 50,
    "manaRegen": 50
  },
  "shop": {
    "prices": {
      "total": 400,
      "combined": 0,
      "sell": 160
    },
    "purchasable": false,
    "tags": [
      "SUPPORT"
    ]
  },
  "iconOverlay": false,
  "maps": [
    11
  ]
}