{
  "name": "Fulmination",
  "id": 443055,
  "tier": 3,
  "rank": [
    "Distributed"
  ],
  "buildsFrom": [],
  "buildsInto": [],
  "specialRecipe": 220007,
  "noEffects": false,
  "removed": false,
  "requiredChampion": "",
  "requiredAlly": "",
  "icon": "https://raw.communitydragon.org/15.10/plugins/rcp-be-lol-game-data/global/default/assets/items/icons2d/3055_fulmination.png",
  "simpleDescription": null,
  "nicknames": [],
  "passives": [
    {
      "unique": true,
      "mythic": false,
      "name": "Energized",
      "effects": "Moving and basic attacking generates ''Energize'' stacks, up to 100.",
      "range": null,
      "cooldown": null,
      "stats": {
        "abilityPower": {
          "flat": 0,
          "percent": 0,
          "perLevel": 0,
          "percentPerLevel": 0,
          "percentBase": 0,
          "percentBonus": 0
        },
        "armor": {
          "flat": 0,
          "percent": 0,
          "perLevel": 0,
          "percentPerLevel": 0,
          "percentBase": 0,
          "percentBonus": 0
        },
        "armorPenetration": {
          "flat": 0,
          "percent": 0,
          "perLevel": 0,
          "percentPerLevel": 0,
          "percentBase": 0,
          "percentBonus": 0
        },
        "attackDamage": {
          "flat": 0,
          "percent": 0,
          "perLevel": 0,
          "percentPerLevel": 0,
          "percentBase": 0,
          "percentBonus": 0
        },
        "attackSpeed": {
          "flat": 0,
          "percent": 0,
          "perLevel": 0,
          "percentPerLevel": 0,
          "percentBase": 0,
          "percentBonus": 0
        },
        "cooldownReduction": {
          "flat": 0,
          "percent": 0,
          "perLevel": 0,
          "percentPerLevel": 0,
          "percentBase": 0,
          "percentBonus": 0
        },
        "criticalStrikeChance": {
          "flat": 0,
          "percent": 0,
          "perLevel": 0,
          "percentPerLevel": 0,
          "percentBase": 0,
          "percentBonus": 0
        },
        "goldPer10": {
          "flat": 0,
          "percent": 0,
          "perLevel": 0,
          "percentPerLevel": 0,
          "percentBase": 0,
          "percentBonus": 0
        },
        "healAndShieldPower": {
          "flat": 0,
          "percent": 0,
          "perLevel": 0,
          "percentPerLevel": 0,
          "percentBase": 0,
          "percentBonus": 0
        },
        "health": {
          "flat": 0,
          "percent": 0,
          "perLevel": 0,
          "percentPerLevel": 0,
          "percentBase": 0,
          "percentBonus": 0
        },
        "healthRegen": {
          "flat": 0,
          "percent": 0,
          "perLevel": 0,
          "percentPerLevel": 0,
          "percentBase": 0,
          "percentBonus": 0
        },
        "lethality": {
          "flat": 0,
          "percent": 0,
          "perLevel": 0,
          "percentPerLevel": 0,
          "percentBase": 0,
          "percentBonus": 0
        },
        "lifesteal": {
          "flat": 0,
          "percent": 0,
          "perLevel": 0,
          "percentPerLevel": 0,
          "percentBase": 0,
          "percentBonus": 0
        },
        "magicPenetration": {
          "flat": 0,
          "percent": 0,
          "perLevel": 0,
          "percentPerLevel": 0,
          "percentBase": 0,
          "percentBonus": 0
        },
        "magicResistance": {
          "flat": 0,
          "percent": 0,
          "perLevel": 0,
          "percentPerLevel": 0,
          "percentBase": 0,
          "percentBonus": 0
        },
        "mana": {
          "flat": 0,
          "percent": 0,
          "perLevel": 0,
          "percentPerLevel": 0,
          "percentBase": 0,
          "percentBonus": 0
        },
        "manaRegen": {
          "flat": 0,
          "percent": 0,
          "perLevel": 0,
          "percentPerLevel": 0,
          "percentBase": 0,
          "percentBonus": 0
        },
        "movespeed": {
          "flat": 0,
          "percent": 0,
          "perLevel": 0,
          "percentPerLevel": 0,
          "percentBase": 0,
          "percentBonus": 0
        },
        "abilityHaste": {
          "flat": 0,
          "percent": 0,
          "perLevel": 0,
          "percentPerLevel": 0,
          "percentBase": 0,
          "percentBonus": 0
        },
        "omnivamp": {
          "flat": 0,
          "percent": 0,
          "perLevel": 0,
          "percentPerLevel": 0,
          "percentBase": 0,
          "percentBonus": 0
        },
        "tenacity": {
          "flat": 0,
          "percent": 0,
          "perLevel": 0,
          "percentPerLevel": 0,
          "percentBase": 0,
          "percentBonus": 0
        },
        "criticalStrikeDamage": {
          "flat": 0,
          "percent": 0,
          "perLevel": 0,
          "percentPerLevel": 0,
          "percentBase": 0,
          "percentBonus": 0
        }
      }
    },
    {
      "unique": true,
      "mythic": false,
      "name": "Polarity",
      "effects": "Your {{tip|Energized}} attacks against targets not hit by your previous ''Energized'' attack do not consume any ''Energize'' stacks on-hit.",
      "range": null,
      "cooldown": null,
      "stats": {
        "abilityPower": {
          "flat": 0,
          "percent": 0,
          "perLevel": 0,
          "percentPerLevel": 0,
          "percentBase": 0,
          "percentBonus": 0
        },
        "armor": {
          "flat": 0,
          "percent": 0,
          "perLevel": 0,
          "percentPerLevel": 0,
          "percentBase": 0,
          "percentBonus": 0
        },
        "armorPenetration": {
          "flat": 0,
          "percent": 0,
          "perLevel": 0,
          "percentPerLevel": 0,
          "percentBase": 0,
          "percentBonus": 0
        },
        "attackDamage": {
          "flat": 0,
          "percent": 0,
          "perLevel": 0,
          "percentPerLevel": 0,
          "percentBase": 0,
          "percentBonus": 0
        },
        "attackSpeed": {
          "flat": 0,
          "percent": 0,
          "perLevel": 0,
          "percentPerLevel": 0,
          "percentBase": 0,
          "percentBonus": 0
        },
        "cooldownReduction": {
          "flat": 0,
          "percent": 0,
          "perLevel": 0,
          "percentPerLevel": 0,
          "percentBase": 0,
          "percentBonus": 0
        },
        "criticalStrikeChance": {
          "flat": 0,
          "percent": 0,
          "perLevel": 0,
          "percentPerLevel": 0,
          "percentBase": 0,
          "percentBonus": 0
        },
        "goldPer10": {
          "flat": 0,
          "percent": 0,
          "perLevel": 0,
          "percentPerLevel": 0,
          "percentBase": 0,
          "percentBonus": 0
        },
        "healAndShieldPower": {
          "flat": 0,
          "percent": 0,
          "perLevel": 0,
          "percentPerLevel": 0,
          "percentBase": 0,
          "percentBonus": 0
        },
        "health": {
          "flat": 0,
          "percent": 0,
          "perLevel": 0,
          "percentPerLevel": 0,
          "percentBase": 0,
          "percentBonus": 0
        },
        "healthRegen": {
          "flat": 0,
          "percent": 0,
          "perLevel": 0,
          "percentPerLevel": 0,
          "percentBase": 0,
          "percentBonus": 0
        },
        "lethality": {
          "flat": 0,
          "percent": 0,
          "perLevel": 0,
          "percentPerLevel": 0,
          "percentBase": 0,
          "percentBonus": 0
        },
        "lifesteal": {
          "flat": 0,
          "percent": 0,
          "perLevel": 0,
          "percentPerLevel": 0,
          "percentBase": 0,
          "percentBonus": 0
        },
        "magicPenetration": {
          "flat": 0,
          "percent": 0,
          "perLevel": 0,
          "percentPerLevel": 0,
          "percentBase": 0,
          "percentBonus": 0
        },
        "magicResistance": {
          "flat": 0,
          "percent": 0,
          "perLevel": 0,
          "percentPerLevel": 0,
          "percentBase": 0,
          "percentBonus": 0
        },
        "mana": {
          "flat": 0,
          "percent": 0,
          "perLevel": 0,
          "percentPerLevel": 0,
          "percentBase": 0,
          "percentBonus": 0
        },
        "manaRegen": {
          "flat": 0,
          "percent": 0,
          "perLevel": 0,
          "percentPerLevel": 0,
          "percentBase": 0,
          "percentBonus": 0
        },
        "movespeed": {
          "flat": 0,
          "percent": 0,
          "perLevel": 0,
          "percentPerLevel": 0,
          "percentBase": 0,
          "percentBonus": 0
        },
        "abilityHaste": {
          "flat": 0,
          "percent": 0,
          "perLevel": 0,
          "percentPerLevel": 0,
          "percentBase": 0,
          "percentBonus": 0
        },
        "omnivamp": {
          "flat": 0,
          "percent": 0,
          "perLevel": 0,
          "percentPerLevel": 0,
          "percentBase": 0,
          "percentBonus": 0
        },
        "tenacity": {
          "flat": 0,
          "percent": 0,
          "perLevel": 0,
          "percentPerLevel": 0,
          "percentBase": 0,
          "percentBonus": 0
        },
        "criticalStrikeDamage": {
          "flat": 0,
          "percent": 0,
          "perLevel": 0,
          "percentPerLevel": 0,
          "percentBase": 0,
          "percentBonus": 0
        }
      }
    },
    {
      "unique": true,
      "mythic": false,
      "name": "Dynamo",
      "effects": "When fully {{tip|Energized}}, your next basic attack deals {{as|'''bonus''' magic damage}} [[on-hit]] equal to {{as|10% of the target's '''current''' health}}.",
      "range": null,
      "cooldown": null,
      "stats": {
        "abilityPower": {
          "flat": 0,
          "percent": 0,
          "perLevel": 0,
          "percentPerLevel": 0,
          "percentBase": 0,
          "percentBonus": 0
        },
        "armor": {
          "flat": 0,
          "percent": 0,
          "perLevel": 0,
          "percentPerLevel": 0,
          "percentBase": 0,
          "percentBonus": 0
        },
        "armorPenetration": {
          "flat": 0,
          "percent": 0,
          "perLevel": 0,
          "percentPerLevel": 0,
          "percentBase": 0,
          "percentBonus": 0
        },
        "attackDamage": {
          "flat": 0,
          "percent": 0,
          "perLevel": 0,
          "percentPerLevel": 0,
          "percentBase": 0,
          "percentBonus": 0
        },
        "attackSpeed": {
          "flat": 0,
          "percent": 0,
          "perLevel": 0,
          "percentPerLevel": 0,
          "percentBase": 0,
          "percentBonus": 0
        },
        "cooldownReduction": {
          "flat": 0,
          "percent": 0,
          "perLevel": 0,
          "percentPerLevel": 0,
          "percentBase": 0,
          "percentBonus": 0
        },
        "criticalStrikeChance": {
          "flat": 0,
          "percent": 0,
          "perLevel": 0,
          "percentPerLevel": 0,
          "percentBase": 0,
          "percentBonus": 0
        },
        "goldPer10": {
          "flat": 0,
          "percent": 0,
          "perLevel": 0,
          "percentPerLevel": 0,
          "percentBase": 0,
          "percentBonus": 0
        },
        "healAndShieldPower": {
          "flat": 0,
          "percent": 0,
          "perLevel": 0,
          "percentPerLevel": 0,
          "percentBase": 0,
          "percentBonus": 0
        },
        "health": {
          "flat": 0,
          "percent": 0,
          "perLevel": 0,
          "percentPerLevel": 0,
          "percentBase": 0,
          "percentBonus": 0
        },
        "healthRegen": {
          "flat": 0,
          "percent": 0,
          "perLevel": 0,
          "percentPerLevel": 0,
          "percentBase": 0,
          "percentBonus": 0
        },
        "lethality": {
          "flat": 0,
          "percent": 0,
          "perLevel": 0,
          "percentPerLevel": 0,
          "percentBase": 0,
          "percentBonus": 0
        },
        "lifesteal": {
          "flat": 0,
          "percent": 0,
          "perLevel": 0,
          "percentPerLevel": 0,
          "percentBase": 0,
          "percentBonus": 0
        },
        "magicPenetration": {
          "flat": 0,
          "percent": 0,
          "perLevel": 0,
          "percentPerLevel": 0,
          "percentBase": 0,
          "percentBonus": 0
        },
        "magicResistance": {
          "flat": 0,
          "percent": 0,
          "perLevel": 0,
          "percentPerLevel": 0,
          "percentBase": 0,
          "percentBonus": 0
        },
        "mana": {
          "flat": 0,
          "percent": 0,
          "perLevel": 0,
          "percentPerLevel": 0,
          "percentBase": 0,
          "percentBonus": 0
        },
        "manaRegen": {
          "flat": 0,
          "percent": 0,
          "perLevel": 0,
          "percentPerLevel": 0,
          "percentBase": 0,
          "percentBonus": 0
        },
        "movespeed": {
          "flat": 0,
          "percent": 0,
          "perLevel": 0,
          "percentPerLevel": 0,
          "percentBase": 0,
          "percentBonus": 0
        },
        "abilityHaste": {
          "flat": 0,
          "percent": 0,
          "perLevel": 0,
          "percentPerLevel": 0,
          "percentBase": 0,
          "percentBonus": 0
        },
        "omnivamp": {
          "flat": 0,
          "percent": 0,
          "perLevel": 0,
          "percentPerLevel": 0,
          "percentBase": 0,
          "percentBonus": 0
        },
        "tenacity": {
          "flat": 0,
          "percent": 0,
          "perLevel": 0,
          "percentPerLevel": 0,
          "percentBase": 0,
          "percentBonus": 0
        },
        "criticalStrikeDamage": {
          "flat": 0,
          "percent": 0,
          "perLevel": 0,
          "percentPerLevel": 0,
          "percentBase": 0,
          "percentBonus": 0
        }
      }
    }
  ],
  "active": [],
  "stats": {
    "attackDamage": 55,
    "attackSpeed": 45,
    "percentMovespeed": 15
  },
  "shop": {
    "prices": {
      "total": 0,
      "combined": 0,
      "sell": 0
    },
    "purchasable": true,
    "tags": [
      "MARKSMAN"
    ]
  },
  "iconOverlay": false,
  "maps": [
    30
  ]
}