{
  "name": "Darksteel Talons",
  "id": 443054,
  "tier": 3,
  "rank": [
    "Special"
  ],
  "buildsFrom": [],
  "buildsInto": [],
  "specialRecipe": 220007,
  "noEffects": false,
  "removed": false,
  "requiredChampion": "",
  "requiredAlly": "",
  "icon": "https://raw.communitydragon.org/15.10/plugins/rcp-be-lol-game-data/global/default/assets/items/icons2d/3054_silversteeltalons.png",
  "simpleDescription": null,
  "nicknames": [],
  "passives": [
    {
      "name": "Gash",
      "unique": true,
      "effects": "Basic attacks on-hit deal {{rd|20 to 40|10 to 20|pp=true}} true damage (+ {{rd|25%|20%}} <b>bonus</b> armor) armor <b>bonus</b> true damage.",
      "cooldown": null,
      "range": null
    }
  ],
  "active": [],
  "stats": {
    "armor": 55,
    "attackSpeed": 50,
    "percentMovespeed": 10
  },
  "shop": {
    "prices": {
      "total": 0,
      "combined": 0,
      "sell": 0
    },
    "purchasable": true,
    "tags": [
      "TANK"
    ]
  },
  "iconOverlay": false,
  "maps": [
    30
  ]
}